clusterenv/__init__.py
clusterenv/_types.py
clusterenv/common.py
clusterenv/envs/cluster.py
clusterenv/render.py
clusterenv/wrappers/__init__.py
clusterenv/wrappers/transform.py
clusterenv-0.3.29.dist-info/METADATA
clusterenv-0.3.29.dist-info/WHEEL
clusterenv-0.3.29.dist-info/RECORD
